[
  {
    "timestamp": 1765172197.500133,
    "total_tasks": 6,
    "completed": 6,
    "valid": 6,
    "errors": 0,
    "elapsed_s": 244.6307337284088,
    "avg_time_per_arch": 40.7717889547348,
    "device_distribution": {
      "cuda:0": 6
    }
  },
  {
    "timestamp": 1765172488.407796,
    "total_tasks": 6,
    "completed": 6,
    "valid": 6,
    "errors": 0,
    "elapsed_s": 290.9064271450043,
    "avg_time_per_arch": 48.48440452416738,
    "device_distribution": {
      "cuda:0": 6
    }
  },
  {
    "timestamp": 1765172737.2972698,
    "total_tasks": 6,
    "completed": 6,
    "valid": 6,
    "errors": 0,
    "elapsed_s": 248.88916277885437,
    "avg_time_per_arch": 41.48152712980906,
    "device_distribution": {
      "cuda:0": 6
    }
  }
]